CattleRealsense/ConvertToPNG.py
CattleRealsense/PictureCapture.py
CattleRealsense/ThresholdExtract.py
CattleRealsense/VideoCapture.py
CattleRealsense/__init__.py
CattleRealsense-0.1.7.dist-info/METADATA
CattleRealsense-0.1.7.dist-info/WHEEL
CattleRealsense-0.1.7.dist-info/top_level.txt
CattleRealsense-0.1.7.dist-info/RECORD
