Metadata-Version: 2.1
Name: CattleRealsense
Version: 0.1.7
Summary: Takes depth video or pictures from birds eye view. Intended for use with cattle
Author: Robert Kadlec
License: UNKNOWN
Platform: UNKNOWN
